odoo9_addon_web_action_conditionable-9.0.1.0.0-py2.7-nspkg.pth
odoo9_addon_web_action_conditionable-9.0.1.0.0.dist-info/DESCRIPTION.rst
odoo9_addon_web_action_conditionable-9.0.1.0.0.dist-info/METADATA
odoo9_addon_web_action_conditionable-9.0.1.0.0.dist-info/RECORD
odoo9_addon_web_action_conditionable-9.0.1.0.0.dist-info/WHEEL
odoo9_addon_web_action_conditionable-9.0.1.0.0.dist-info/metadata.json
odoo9_addon_web_action_conditionable-9.0.1.0.0.dist-info/namespace_packages.txt
odoo9_addon_web_action_conditionable-9.0.1.0.0.dist-info/top_level.txt
odoo_addons/web_action_conditionable/README.rst
odoo_addons/web_action_conditionable/__init__.py
odoo_addons/web_action_conditionable/__openerp__.py
odoo_addons/web_action_conditionable/static/description/icon.png
odoo_addons/web_action_conditionable/static/src/js/views.js
odoo_addons/web_action_conditionable/views/view.xml
